<ModOps>
  <!-- Test Specialist aka DolphinTest-->
  <Group>
    <ModOp Add="/TextExport/Texts">
      <!-- Title -->
      <Text>
          <Text>Dolphin Test Specialist</Text>
          <LineId>2001000001</LineId>
      </Text>
      <!-- Description -->
      <Text>
          <Text>Meb Meb! Test Description</Text>
          <LineId>2001000002</LineId>
      </Text>
    </ModOp>
  </Group>
  
  <!-- Specialist AllPublicServicesRange C -->
  <Group>
    <ModOp Add="/TextExport/Texts">
      <!-- Title -->
      <Text>
          <Text>Specialist AllPublicServicesRange C Title</Text>
          <LineId>2001000003</LineId>
      </Text>
      <!-- Description -->
      <Text>
          <Text>Specialist AllPublicServicesRange C Description</Text>
          <LineId>2001000004</LineId>
      </Text>
    </ModOp>
  </Group>

   <!-- Specialist AllPublicServicesRange R -->
  <Group>
    <ModOp Add="/TextExport/Texts">
      <!-- Title -->
      <Text>
          <Text>Specialist AllPublicServicesRange R Title</Text>
          <LineId>2001000005</LineId>
      </Text>
      <!-- Description -->
      <Text>
          <Text>Specialist AllPublicServicesRange R Description</Text>
          <LineId>2001000006</LineId>
      </Text>
    </ModOp>
  </Group>

  <!-- Specialist AllPublicServicesRange E -->
  <Group>
    <ModOp Add="/TextExport/Texts">
      <!-- Title -->
      <Text>
          <Text>Specialist AllPublicServicesRange E Title</Text>
          <LineId>2001000007</LineId>
      </Text>
      <!-- Description -->
      <Text>
          <Text>Specialist AllPublicServicesRange E Description</Text>
          <LineId>2001000008</LineId>
      </Text>
    </ModOp>
  </Group>

  <!-- Specialist MarketFaithFocus C -->
  <Group>
    <ModOp Add="/TextExport/Texts">
      <!-- Title -->
      <Text>
          <Text>Specialist MarketFaithFocus C Title</Text>
          <LineId>2001000009</LineId>
      </Text>
      <!-- Description -->
      <Text>
          <Text>Specialist MarketFaithFocus C Description</Text>
          <LineId>2001000010</LineId>
      </Text>
    </ModOp>
  </Group>
</ModOps>